<?xml version="1.0"?><results category='Media contributed by Göteborgs konstmuseum' images_in_category='644' query_url='glamorous.php?doit=1&amp;category=Media+contributed+by+G%C3%B6teborgs+konstmuseum&amp;use_globalusage=1&amp;ns0=1&amp;depth=9&amp;projects[wikipedia]=1&amp;projects[wikimedia]=1&amp;projects[wikisource]=1&amp;projects[wikibooks]=1&amp;projects[wikiquote]=1&amp;projects[wiktionary]=1&amp;projects[wikinews]=1&amp;projects[wikivoyage]=1&amp;projects[wikispecies]=1&amp;projects[mediawiki]=1&amp;projects[wikidata]=1&amp;projects[wikiversity]=1&amp;format=xml'><stats total_usage='901' distinct_images='393'><usage project='wikidata.wikidata' usage_count='374' /><usage project='sv.wikipedia' usage_count='124' /><usage project='en.wikipedia' usage_count='112' /><usage project='de.wikipedia' usage_count='40' /><usage project='da.wikipedia' usage_count='38' /><usage project='fr.wikipedia' usage_count='26' /><usage project='pt.wikipedia' usage_count='20' /><usage project='es.wikipedia' usage_count='19' /><usage project='et.wikiquote' usage_count='18' /><usage project='nl.wikipedia' usage_count='15' /><usage project='ru.wikipedia' usage_count='14' /><usage project='fi.wikipedia' usage_count='14' /><usage project='ja.wikipedia' usage_count='12' /><usage project='it.wikipedia' usage_count='9' /><usage project='no.wikipedia' usage_count='6' /><usage project='tr.wikipedia' usage_count='5' /><usage project='ko.wikipedia' usage_count='5' /><usage project='outreach.wikipedia' usage_count='4' /><usage project='se.wikimedia' usage_count='3' /><usage project='ar.wikipedia' usage_count='3' /><usage project='ca.wikipedia' usage_count='3' /><usage project='cs.wikipedia' usage_count='3' /><usage project='meta.wikipedia' usage_count='3' /><usage project='hu.wikipedia' usage_count='3' /><usage project='fa.wikipedia' usage_count='2' /><usage project='he.wikipedia' usage_count='2' /><usage project='sl.wikipedia' usage_count='2' /><usage project='en.wiktionary' usage_count='2' /><usage project='en.wikiquote' usage_count='2' /><usage project='zh.wikipedia' usage_count='2' /><usage project='pl.wikipedia' usage_count='2' /><usage project='bs.wikipedia' usage_count='1' /><usage project='lv.wikipedia' usage_count='1' /><usage project='sw.wikipedia' usage_count='1' /><usage project='hy.wikipedia' usage_count='1' /><usage project='ast.wikipedia' usage_count='1' /><usage project='bg.wikipedia' usage_count='1' /><usage project='ku.wikipedia' usage_count='1' /><usage project='id.wikipedia' usage_count='1' /><usage project='et.wikipedia' usage_count='1' /><usage project='ckb.wikipedia' usage_count='1' /><usage project='az.wikipedia' usage_count='1' /><usage project='arz.wikipedia' usage_count='1' /><usage project='bn.wikipedia' usage_count='1' /><usage project='af.wikipedia' usage_count='1' /></stats></results>